<?xml version="1.0"?>
<!DOCTYPE package-info SYSTEM "http://www.simplemachines.org/xml/package-info">

<package-info xmlns="http://www.simplemachines.org/xml/package-info" xmlns:smf="http://www.simplemachines.org/">
	<id>Dougiefresh:YouTube</id>
	<name>Yet Another YouTube BBCode Tag</name>
	<type>modification</type>
	<version>1.2</version>

	<install for="2.0 - 2.0.99">
		<readme parsebbc="true">readme.txt</readme>
		<code>add_remove_hooks.php</code>
		<modification>install.xml</modification>
		<modification>language.english.xml</modification>
		<require-file name="Subs-BBCode-YouTube.php" destination="$sourcedir" />
		<require-file name="youtube.gif" destination="$themedir/images/bbc" />
	</install>
	<uninstall for="2.0 - 2.0.99">
		<code>add_remove_hooks.php</code>
		<modification reverse="true">install.xml</modification>
		<modification reverse="true">language.english.xml</modification>
		<remove-file name="$sourcedir/Subs-BBCode-YouTube.php" />
		<remove-file name="$themedir/images/bbc/youtube.gif" />
	</uninstall>
</package-info>